setup.py
thebot_translate.py
thebot_translate.egg-info/PKG-INFO
thebot_translate.egg-info/SOURCES.txt
thebot_translate.egg-info/dependency_links.txt
thebot_translate.egg-info/requires.txt
thebot_translate.egg-info/top_level.txt