Metadata-Version: 1.1
Name: thebot-translate
Version: 0.1.1
Summary: Uses translate.yandex.ru, to translate the texts.
Home-page: http://github.com/svetlyak40wt/thebot-translate/
Author: Alexander Artemenko
Author-email: svetlyak.40wt@gmail.com
License: New BSD License
Keywords: thebot language plugin
Platform: UNKNOWN
Classifier: Development Status :: 4 - Beta
Classifier: Environment :: Plugins
Classifier: Intended Audience :: Developers
Classifier: Intended Audience :: System Administrators
Classifier: License :: OSI Approved :: BSD License
Classifier: Programming Language :: Python
